LICENSE
README.md
setup.cfg
setup.py
dcase_util/__init__.py
dcase_util.egg-info/PKG-INFO
dcase_util.egg-info/SOURCES.txt
dcase_util.egg-info/dependency_links.txt
dcase_util.egg-info/requires.txt
dcase_util.egg-info/top_level.txt
dcase_util/containers/__init__.py
dcase_util/containers/audio.py
dcase_util/containers/containers.py
dcase_util/containers/data.py
dcase_util/containers/features.py
dcase_util/containers/mapping.py
dcase_util/containers/metadata.py
dcase_util/containers/mixins.py
dcase_util/containers/parameters.py
dcase_util/containers/probability.py
dcase_util/data/__init__.py
dcase_util/data/buffers.py
dcase_util/data/decisions.py
dcase_util/data/encoders.py
dcase_util/data/manipulators.py
dcase_util/data/probabilities.py
dcase_util/datasets/__init__.py
dcase_util/datasets/datasets.py
dcase_util/datasets/dcase2013.py
dcase_util/datasets/dcase2016.py
dcase_util/datasets/dcase2017.py
dcase_util/datasets/dcase2018.py
dcase_util/datasets/tut.py
dcase_util/decorators/__init__.py
dcase_util/decorators/decorators.py
dcase_util/features/__init__.py
dcase_util/features/features.py
dcase_util/files/__init__.py
dcase_util/files/files.py
dcase_util/files/remote.py
dcase_util/files/serialization.py
dcase_util/keras/__init__.py
dcase_util/keras/callbacks.py
dcase_util/keras/data.py
dcase_util/keras/model.py
dcase_util/keras/utils.py
dcase_util/processors/__init__.py
dcase_util/processors/audio.py
dcase_util/processors/data.py
dcase_util/processors/encoders.py
dcase_util/processors/features.py
dcase_util/processors/metadata.py
dcase_util/processors/processing_chain.py
dcase_util/processors/processor.py
dcase_util/tfkeras/__init__.py
dcase_util/tfkeras/callbacks.py
dcase_util/tfkeras/data.py
dcase_util/tfkeras/model.py
dcase_util/tfkeras/utils.py
dcase_util/tools/__init__.py
dcase_util/tools/bibtex.py
dcase_util/tools/datasets.py
dcase_util/tools/submission.py
dcase_util/ui/__init__.py
dcase_util/ui/ui.py
dcase_util/utils/__init__.py
dcase_util/utils/examples.py
dcase_util/utils/files.py
dcase_util/utils/hash.py
dcase_util/utils/logging.py
dcase_util/utils/math.py
dcase_util/utils/timer.py
dcase_util/utils/utils.py
