Metadata-Version: 2.1
Name: dcase-util
Version: 0.2.20
Summary: A collection of utilities for Detection and Classification of Acoustic Scenes and Events
Home-page: https://github.com/DCASE-REPO/dcase_util
Author: Toni Heittola
Author-email: toni.heittola@gmail.com
License: MIT
Download-URL: https://github.com/DCASE-REPO/dcase_util/releases
Keywords: audio sound
Platform: UNKNOWN
Classifier: License :: OSI Approved :: MIT License
Classifier: Programming Language :: Python
Classifier: Development Status :: 5 - Production/Stable
Classifier: Intended Audience :: Developers
Classifier: Topic :: Multimedia :: Sound/Audio :: Analysis
Classifier: Topic :: Scientific/Engineering :: Artificial Intelligence
Classifier: Programming Language :: Python :: 2.7
Classifier: Programming Language :: Python :: 3.6
License-File: LICENSE
